BeemAfrica/AirTime.py
BeemAfrica/Bpay.py
BeemAfrica/OTP.py
BeemAfrica/SMS.py
BeemAfrica/TwowaySMS.py
BeemAfrica/USSD.py
BeemAfrica/__init__.py
beem_africa-0.1.2.dist-info/LICENSE
beem_africa-0.1.2.dist-info/METADATA
beem_africa-0.1.2.dist-info/WHEEL
beem_africa-0.1.2.dist-info/top_level.txt
beem_africa-0.1.2.dist-info/RECORD
