Metadata-Version: 2.1
Name: beem-africa
Version: 0.1.2
Summary: A Python library to easy the integration with the Beem Africa SMS Gateway
Home-page: https://github.com/beem-africa/python-client
Author: Jordan Kalebu
Author-email: isaackeinstein@gmail.com
License: MIT
Download-URL: https://github.com/beem-africa/python-client/releases/tag/0.1
Keywords: beem-africa,beem-sms-api,python-beem,beem africa  package,beem-africa-python,python-tanzania
Platform: UNKNOWN
Classifier: Development Status :: 3 - Alpha
Classifier: Intended Audience :: Developers
Classifier: Topic :: Software Development :: Build Tools
Classifier: License :: OSI Approved :: MIT License
Classifier: Programming Language :: Python :: 3.6
Classifier: Programming Language :: Python :: 3.7
Classifier: Programming Language :: Python :: 3.8
Classifier: Programming Language :: Python :: 3.9
Requires-Python: >=3.6
